gfypy/__init__.py
gfypy/const.py
gfypy/exceptions.py
gfypy/gfy.py
gfypy/helpers.py
gfypy/route.py
gfypy/user.py
gfypy/version.py
gfypy/client/__init__.py
gfypy/client/abstract_client.py
gfypy/client/async_client.py
gfypy/client/sync_client.py
gfypy/http/__init__.py
gfypy/http/abstract_http.py
gfypy/http/async_http.py
gfypy/http/sync_http.py
gfypy-1.2.4.data/scripts/gfy-uploader
gfypy-1.2.4.dist-info/LICENSE
gfypy-1.2.4.dist-info/METADATA
gfypy-1.2.4.dist-info/WHEEL
gfypy-1.2.4.dist-info/top_level.txt
gfypy-1.2.4.dist-info/RECORD
