Metadata-Version: 2.1
Name: gfypy
Version: 1.2.4
Summary: Python wrapper for the Gfycat API
Home-page: https://github.com/noahkw/gfypy
Author: Noah K W
Author-email: noah@dreckbu.de
License: MIT
Keywords: gfycat api wrapper
Platform: UNKNOWN
Classifier: Development Status :: 3 - Alpha
Classifier: Intended Audience :: Developers
Classifier: License :: OSI Approved :: MIT License
Classifier: Programming Language :: Python :: 3.6
Classifier: Programming Language :: Python :: 3.7
Classifier: Programming Language :: Python :: 3.8
Requires-Dist: requests
Requires-Dist: tqdm
Provides-Extra: async
Requires-Dist: aiohttp ; extra == 'async'
